decoratio/__init__.py
decoratio/__main__.py
decoratio-1.0.5.dist-info/LICENSE
decoratio-1.0.5.dist-info/METADATA
decoratio-1.0.5.dist-info/WHEEL
decoratio-1.0.5.dist-info/top_level.txt
decoratio-1.0.5.dist-info/RECORD
