Metadata-Version: 2.1
Name: decoratio
Version: 1.0.5
Summary: A bioinformatics package to estimate the depth-complexity ratio and amplification noisiness of a sequencing experiment.
Author-email: "Nicolas C. Rochette" <nic.rochette@gmail.com>, "Angel G. Rivera-Colon" <angelgr2@illinois.edu>, "Julian M. Catchen" <jcatchen@illinois.edu>
Project-URL: Source, https://bitbucket.org/rochette/decoratio/
Project-URL: Bugs & Issues, https://bitbucket.org/rochette/decoratio/issues
Classifier: Programming Language :: Python :: 3
Classifier: Operating System :: OS Independent
Classifier: License :: OSI Approved :: GNU General Public License v3 or later (GPLv3+)
Requires-Python: >=3.5
License-File: LICENSE
Requires-Dist: numpy
Requires-Dist: scipy
Requires-Dist: matplotlib
